MANIFEST.in
requirements.txt
setup.py
codalabworker/__init__.py
codalabworker/bundle_service_client.py
codalabworker/bundle_state.py
codalabworker/docker_utils.py
codalabworker/download_util.py
codalabworker/file_util.py
codalabworker/formatting.py
codalabworker/fsm.py
codalabworker/main.py
codalabworker/pyjson.py
codalabworker/rest_client.py
codalabworker/run_manager.py
codalabworker/state_committer.py
codalabworker/worker.py
codalabworker/worker_thread.py
codalabworker.egg-info/PKG-INFO
codalabworker.egg-info/SOURCES.txt
codalabworker.egg-info/dependency_links.txt
codalabworker.egg-info/entry_points.txt
codalabworker.egg-info/not-zip-safe
codalabworker.egg-info/requires.txt
codalabworker.egg-info/top_level.txt
codalabworker/local_run/__init__.py
codalabworker/local_run/docker_image_manager.py
codalabworker/local_run/local_dependency_manager.py
codalabworker/local_run/local_reader.py
codalabworker/local_run/local_run_manager.py
codalabworker/local_run/local_run_state.py