Metadata-Version: 1.2
Name: codalabworker
Version: 0.3.2
Summary: Worker for CodaLab, a platform for reproducible computation
Home-page: https://github.com/codalab/codalab-worksheets
Author: CodaLab
Author-email: codalab.worksheets@gmail.com
License: Apache License 2.0
Keywords: codalab reproducible computation worksheets competitions worker
Platform: UNKNOWN
Classifier: Programming Language :: Python :: 2 :: Only
Classifier: Programming Language :: Python :: 2.7
Classifier: License :: OSI Approved :: Apache Software License
Requires-Python: ~=2.7
